py4D_browser/__init__.py
py4D_browser/dialogs.py
py4D_browser/help_menu.py
py4D_browser/logo.png
py4D_browser/main_window.py
py4D_browser/menu_actions.py
py4D_browser/plugins.py
py4D_browser/py4DGUI-keymap.png
py4D_browser/runGUI.py
py4D_browser/scalebar.py
py4D_browser/update_views.py
py4D_browser/utils.py
py4d_browser-1.3.1.dist-info/licenses/LICENSE.txt
py4d_browser_plugin/calibration_plugin/__init__.py
py4d_browser_plugin/calibration_plugin/calibration_plugin.py
py4d_browser_plugin/placeholder/__init__.py
py4d_browser_plugin/tcBF_plugin/__init__.py
py4d_browser_plugin/tcBF_plugin/tcBF_plugin.py
py4d_browser-1.3.1.dist-info/METADATA
py4d_browser-1.3.1.dist-info/WHEEL
py4d_browser-1.3.1.dist-info/entry_points.txt
py4d_browser-1.3.1.dist-info/top_level.txt
py4d_browser-1.3.1.dist-info/RECORD
