Metadata-Version: 2.4
Name: py4D_browser
Version: 1.3.1
Summary: A 4D-STEM data browser built on py4DSTEM.
Author-email: Steven Zeltmann <steven.zeltmann@lbl.gov>
Project-URL: Homepage, https://github.com/py4dstem/py4D-browser
Project-URL: Bug Tracker, https://github.com/py4dstem/py4D-browser/issues
Classifier: Programming Language :: Python :: 3
Classifier: Operating System :: OS Independent
Requires-Python: >=3.11
License-File: LICENSE.txt
Requires-Dist: py4dstem>=0.14.9
Requires-Dist: emdfile>=0.0.11
Requires-Dist: h5py
Requires-Dist: numpy>=1.19
Requires-Dist: matplotlib>=3.2.2
Requires-Dist: platformdirs
Requires-Dist: PyQt5>=5.10
Requires-Dist: pyqtgraph>=0.11
Requires-Dist: sigfig
Dynamic: license-file
